[
    {
        "transactionName": "open_site",
        "rawStartTime": 1595496161264,
        "rawEndTime": 1595496161999
    },
    {
        "transactionName": "Login",
        "rawStartTime": 1595496162101,
        "rawEndTime": 1595496162602
    },
    {
        "transactionName": "Flights_click",
        "rawStartTime": 1595496162697,
        "rawEndTime": 1595496163229
    },
    {
        "transactionName": "Find_flight",
        "rawStartTime": 1595496163321,
        "rawEndTime": 1595496164002
    },
    {
        "transactionName": "Choose_flight",
        "rawStartTime": 1595496164126,
        "rawEndTime": 1595496164493
    },
    {
        "transactionName": "Insert_payment_details",
        "rawStartTime": 1595496164595,
        "rawEndTime": 1595496165005
    },
    {
        "transactionName": "Logout",
        "rawStartTime": 1595496165116,
        "rawEndTime": 1595496165571
    },
    {
        "transactionName": "04_Buy_ticket_without_check_itenerary",
        "rawStartTime": 1595496161203,
        "rawEndTime": 1595496165853
    }
]